lektor_tailwind.py
lektor_tailwind-0.3.0.dist-info/licenses/LICENSE
lektor_tailwind-0.3.0.dist-info/METADATA
lektor_tailwind-0.3.0.dist-info/WHEEL
lektor_tailwind-0.3.0.dist-info/entry_points.txt
lektor_tailwind-0.3.0.dist-info/top_level.txt
lektor_tailwind-0.3.0.dist-info/RECORD
