Metadata-Version: 2.4
Name: lektor-tailwind
Version: 0.3.0
Summary: A Lektor plugin that adds Tailwind CSS to your project seamlessly.
Home-page: https://github.com/frostming/lektor-tailwind
Author: Frost Ming
Author-email: mianghong@gmail.com
License: MIT
Classifier: Development Status :: 4 - Beta
Classifier: Framework :: Lektor
Classifier: Programming Language :: Python
Classifier: Programming Language :: Python :: 3
Classifier: Programming Language :: Python :: 3.10
Classifier: Programming Language :: Python :: 3.11
Classifier: Programming Language :: Python :: 3.12
Classifier: Programming Language :: Python :: 3.8
Classifier: Programming Language :: Python :: 3.9
Requires-Python: >=3.8
License-File: LICENSE
Requires-Dist: pytailwindcss>=0.1.4
Dynamic: license-file
